geocollector/__init__.py
geocollector/api.py
geocollector/cli.py
geocollector/logger.py
geocollector/main.py
geocollector/records.py
geocollector-1.1.3.dist-info/METADATA
geocollector-1.1.3.dist-info/WHEEL
geocollector-1.1.3.dist-info/entry_points.txt
geocollector-1.1.3.dist-info/RECORD
