Metadata-Version: 2.1
Name: geocollector
Version: 1.1.3
Summary: Collect information from NCBI for the https://github.com/HelikarLab/FastqToGeneCounts project
Home-page: https://github.com/JoshLoecker/GEOcollector
Author: Josh Loecker
Author-email: joshloecker@icloud.com
Requires-Python: >=3.8
Classifier: Programming Language :: Python :: 3
Classifier: Programming Language :: Python :: 3.8
Classifier: Programming Language :: Python :: 3.9
Classifier: Programming Language :: Python :: 3.10
Classifier: Programming Language :: Python :: 3.11
Requires-Dist: aiohttp (>=3.8.5)
Requires-Dist: pandas (>=1.5.3)
Requires-Dist: tqdm (>=4.66.1)
Project-URL: Repository, https://github.com/JoshLoecker/GEOcollector
